print_arabic.py
print_arabic-0.1.dist-info/licenses/LICENSE
print_arabic-0.1.dist-info/METADATA
print_arabic-0.1.dist-info/WHEEL
print_arabic-0.1.dist-info/top_level.txt
print_arabic-0.1.dist-info/RECORD
